HeartbeatsData/__init__.py
HeartbeatsData/heartbeats_data.py
HeartbeatsData-1.0.0.dist-info/LICENSE
HeartbeatsData-1.0.0.dist-info/METADATA
HeartbeatsData-1.0.0.dist-info/WHEEL
HeartbeatsData-1.0.0.dist-info/top_level.txt
HeartbeatsData-1.0.0.dist-info/RECORD
