Metadata-Version: 2.1
Name: HeartbeatsData
Version: 1.0.0
Summary: Heartbeat data plotter for matplotlib
Author-email: hopperelec <hopperelec@gmail.com>
License: Attribution-ShareAlike 4.0 International
Project-URL: Homepage, https://github.com/hopperelec/HeartbeatsData
Project-URL: Bug Tracker, https://github.com/hopperelec/HeartbeatsData/issues
Classifier: Programming Language :: Python :: 3
Classifier: License :: Free To Use But Restricted
Classifier: Operating System :: OS Independent
Requires-Python: >=3.7
License-File: LICENSE
